resolver/__init__.py
resolver/from_json.py
resolver/to_json.py
sceptre_json_resolver-1.0.0.dist-info/METADATA
sceptre_json_resolver-1.0.0.dist-info/WHEEL
sceptre_json_resolver-1.0.0.dist-info/entry_points.txt
sceptre_json_resolver-1.0.0.dist-info/RECORD
