Metadata-Version: 2.3
Name: sceptre-json-resolver
Version: 1.0.0
Summary: A Sceptre resolver to serialize and deserialize json
License: Apache-2.0
Keywords: sceptre,sceptre-resolver
Author: Sceptre
Author-email: sceptreorg@gmail.com
Requires-Python: >=3.9,<4.0
Classifier: Environment :: Console
Classifier: Intended Audience :: Developers
Classifier: License :: OSI Approved :: Apache Software License
Classifier: Natural Language :: English
Classifier: Programming Language :: Python :: 3
Classifier: Programming Language :: Python :: 3.9
Classifier: Programming Language :: Python :: 3.10
Classifier: Programming Language :: Python :: 3.11
Classifier: Programming Language :: Python :: 3.12
Classifier: Programming Language :: Python :: 3.13
Project-URL: Homepage, https://github.com/Sceptre/sceptre-json-resolver
Project-URL: Repository, https://github.com/Sceptre/sceptre-json-resolver
